httpie_oauth2_client_credentials_flow.py
httpie_oauth2_client_credentials_flow-0.3.0.dist-info/LICENSE
httpie_oauth2_client_credentials_flow-0.3.0.dist-info/METADATA
httpie_oauth2_client_credentials_flow-0.3.0.dist-info/WHEEL
httpie_oauth2_client_credentials_flow-0.3.0.dist-info/entry_points.txt
httpie_oauth2_client_credentials_flow-0.3.0.dist-info/top_level.txt
httpie_oauth2_client_credentials_flow-0.3.0.dist-info/RECORD
