Metadata-Version: 2.1
Name: httpie-oauth2-client-credentials-flow
Version: 0.3.0
Summary: httpie auth plugin for OAuth2.0 client credentials flow.
Home-page: https://github.com/cliffcotino/httpie-oauth2-client-credentials
Download-URL: https://github.com/cliffcotino/httpie-oauth2-client-credentials
Author: satdoc
Author-email: satodoc-develop-public@outlook.com
Maintainer: cliffcotino
Maintainer-email: cliffcotino@gmail.com
License: MIT
Classifier: Development Status :: 4 - Beta
Classifier: Programming Language :: Python
Classifier: Intended Audience :: Developers
Classifier: Environment :: Console
Classifier: Environment :: Plugins
Classifier: License :: OSI Approved :: MIT License
Classifier: Topic :: Internet :: WWW/HTTP
Classifier: Topic :: Utilities
License-File: LICENSE
Requires-Dist: httpie >=3.2.2
Requires-Dist: pyjwt[crypto] >=2.8.0
Provides-Extra: testing
Requires-Dist: pytest ; extra == 'testing'
Requires-Dist: pytest-cov ; extra == 'testing'
Requires-Dist: pytest-httpserver ; extra == 'testing'
Requires-Dist: werkzeug ; extra == 'testing'
